voxsynth/__init__.py
voxsynth-0.0.1.dist-info/METADATA
voxsynth-0.0.1.dist-info/WHEEL
voxsynth-0.0.1.dist-info/top_level.txt
voxsynth-0.0.1.dist-info/RECORD
