Metadata-Version: 2.4
Name: voxsynth
Version: 0.0.1
Summary: Voice synthesis and audio pipeline utilities
Author-email: David Nobles <david.nobles@sontric.org>
License: Apache-2.0
Project-URL: Homepage, https://github.com/yourname/voxsynth
Requires-Python: >=3.9
